edrpou/__init__.py
edrpou-1.3.dist-info/LICENSE.txt
edrpou-1.3.dist-info/METADATA
edrpou-1.3.dist-info/WHEEL
edrpou-1.3.dist-info/top_level.txt
edrpou-1.3.dist-info/RECORD
