Metadata-Version: 2.1
Name: edrpou
Version: 1.3
Summary: Ukrainian EDRPOU-IIN validation
Home-page: https://github.com/pablissimo77/edrpou-iin-validation/
Author: Pavlo Yaremchuk (pablissimo77)
Author-email: pablissimo77@gmail.com
License: UNKNOWN
Platform: UNKNOWN
Classifier: Programming Language :: Python :: 3
Classifier: License :: OSI Approved :: MIT License
Classifier: Operating System :: OS Independent
Classifier: Topic :: Utilities
